LICENSE
README.md
setup.cfg
setup.py
jupiterweb/__init__.py
jupiterweb/api.py
jupiterweb/exceptions.py
jupiterweb.egg-info/PKG-INFO
jupiterweb.egg-info/SOURCES.txt
jupiterweb.egg-info/dependency_links.txt
jupiterweb.egg-info/requires.txt
jupiterweb.egg-info/top_level.txt