Metadata-Version: 2.1
Name: jupiterweb
Version: 1.4.1
Summary: Um scraper de disciplinas do jupiterweb
Home-page: https://github.com/ghurone/jupiterweb_scraper
Author: Erick Ghuron
Author-email: ghuron@usp.br
License: MIT
Project-URL: Código fonte, https://github.com/ghurone/jupiterweb_scraper
Keywords: jupiterweb disciplinas usp ghuron
Classifier: Development Status :: 5 - Production/Stable
Classifier: Intended Audience :: Developers
Classifier: License :: OSI Approved :: MIT License
Classifier: Natural Language :: Portuguese (Brazilian)
Classifier: Operating System :: OS Independent
Requires-Python: >=3.8
License-File: LICENSE
